primecountpy/__init__.py
primecountpy/defs.pxd
primecountpy/primecount.cpython-314t-x86_64-linux-gnu.so
primecountpy.libs/libgomp-e985bcbb.so.1.0.0
primecountpy-0.2.1.dist-info/LICENSE
primecountpy-0.2.1.dist-info/METADATA
primecountpy-0.2.1.dist-info/WHEEL
primecountpy-0.2.1.dist-info/RECORD
primecountpy-0.2.1.dist-info/sboms/auditwheel.cdx.json
