Metadata-Version: 2.1
Name: primecountpy
Version: 0.2.1
Summary: Cython interface for C++ primecount library
Author-Email: SageMath Developers <sage-devel@googlegroups.com>
License:                     GNU GENERAL PUBLIC LICENSE
Classifier: Development Status :: 3 - Alpha
Classifier: Intended Audience :: Science/Research
Classifier: Programming Language :: Python :: 3
Classifier: Topic :: Scientific/Engineering :: Mathematics
Project-URL: Homepage, https://github.com/dimpase/primecountpy
Project-URL: User Manual, https://primecountpy.readthedocs.io
Project-URL: Bug Tracker, https://github.com/dimpase/primecountpy/issues
Requires-Python: >=3.11
Requires-Dist: cysignals
Provides-Extra: doc
Requires-Dist: sphinx; extra == "doc"
Requires-Dist: myst_parser; extra == "doc"
